{
  "gitSyncId": "68bf46d3c4f12e2bf17c39f9_2af3b590-dc6a-4efb-897d-b2123f0be2e7",
  "id": "gestion_metas_utils.disbursePayment",
  "pluginId": "js-plugin",
  "pluginType": "JS",
  "unpublishedAction": {
    "actionConfiguration": {
      "encodeParamsToggle": true,
      "isAsync": true,
      "jsArguments": [],
      "paginationType": "NONE",
      "timeoutInMillisecond": 10000
    },
    "collectionId": "gestion_metas_utils",
    "confirmBeforeExecute": false,
    "datasource": {
      "isAutoGenerated": false,
      "name": "UNUSED_DATASOURCE",
      "pluginId": "js-plugin"
    },
    "dynamicBindingPathList": [
      {
        "key": "body"
      }
    ],
    "fullyQualifiedName": "utils.disbursePayment",
    "name": "disbursePayment",
    "pageId": "gestion_metas",
    "runBehaviour": "MANUAL",
    "userSetOnLoad": false
  }
}